naas_abi_cli/__init__.py
naas_abi_cli/cli/__init__.py
naas_abi_cli/cli/agent.py
naas_abi_cli/cli/chat.py
naas_abi_cli/cli/config.py
naas_abi_cli/cli/deploy.py
naas_abi_cli/cli/init.py
naas_abi_cli/cli/module.py
naas_abi_cli/cli/run.py
naas_abi_cli/cli/secret.py
naas_abi_cli/cli/new/__init__.py
naas_abi_cli/cli/new/module.py
naas_abi_cli/cli/new/new.py
naas_abi_cli/cli/new/project.py
naas_abi_cli/cli/new/utils.py
naas_abi_cli/cli/new/templates/module/__init__.py
naas_abi_cli/cli/new/templates/module/agents/README.md
naas_abi_cli/cli/new/templates/module/agents/{{module_name_pascal}}Agent.py
naas_abi_cli/cli/new/templates/module/orchestrations/README.md
naas_abi_cli/cli/new/templates/module/pipelines/README.md
naas_abi_cli/cli/new/templates/module/workflows/README.md
naas_abi_cli/cli/new/templates/project/.gitignore
naas_abi_cli/cli/new/templates/project/Dockerfile
naas_abi_cli/cli/new/templates/project/README.md
naas_abi_cli/cli/new/templates/project/pyproject.toml
naas_abi_cli/cli/new/templates/project/.github/workflows/release.yaml
naas_abi_cli/cli/utils/Copier.py
naas_abi_cli/cli/new/templates/project/config.prod.yaml
naas_abi_cli/cli/new/templates/project/config.yaml
naas_abi_cli-1.9.1.dist-info/METADATA
naas_abi_cli-1.9.1.dist-info/WHEEL
naas_abi_cli-1.9.1.dist-info/entry_points.txt
naas_abi_cli-1.9.1.dist-info/RECORD
