Metadata-Version: 2.4
Name: naas-abi-cli
Version: 1.9.1
Summary: Abi cli allowing you to build your AI system.
Project-URL: Homepage, https://github.com/jupyter-naas/abi
Project-URL: Repository, https://github.com/jupyter-naas/abi/tree/main/libs/naas-abi-cli
Author-email: Maxime Jublou <maxime@naas.ai>, Florent Ravenel <florent@naas.ai>, Jeremy Ravenel <jeremy@naas.ai>
License: MIT License
Requires-Python: <4,>=3.10
Requires-Dist: naas-abi-core[qdrant]>=1.4.0
Requires-Dist: naas-abi-marketplace[ai-chatgpt]>=1.3.3
Requires-Dist: naas-abi>=1.0.11
